{"c887e030d98c88ac65a606be7411ef2e":{"statistic":{"failed":0,"broken":0,"skipped":0,"passed":1,"unknown":0,"total":1},"items":[{"uid":"e533323cb0ff79cf","reportUrl":"https://zakharovyn.github.io/autotests-ui/3/#testresult/e533323cb0ff79cf","status":"passed","time":{"start":1771497753904,"stop":1771497753904,"duration":0}}]},"d47b3316f958ad5f4e040ba9455f262c":{"statistic":{"failed":0,"broken":0,"skipped":0,"passed":1,"unknown":0,"total":1},"items":[{"uid":"3e1d2a2fb367dabb","reportUrl":"https://zakharovyn.github.io/autotests-ui/3/#testresult/3e1d2a2fb367dabb","status":"passed","time":{"start":1771497753895,"stop":1771497753895,"duration":0}}]},"d8c505e45a0342d1f1291ba827195fda":{"statistic":{"failed":0,"broken":0,"skipped":0,"passed":1,"unknown":0,"total":1},"items":[{"uid":"501d5753f1117339","reportUrl":"https://zakharovyn.github.io/autotests-ui/3/#testresult/501d5753f1117339","status":"passed","time":{"start":1771497747098,"stop":1771497748800,"duration":1702}}]},"1ac91e93209424695453f5bd9839e52d":{"statistic":{"failed":0,"broken":0,"skipped":0,"passed":1,"unknown":0,"total":1},"items":[{"uid":"1f75621cd75b5b19","reportUrl":"https://zakharovyn.github.io/autotests-ui/3/#testresult/1f75621cd75b5b19","status":"passed","time":{"start":1771497752410,"stop":1771497754928,"duration":2518}}]},"286be676f5f59009ab00966f91528b11":{"statistic":{"failed":0,"broken":0,"skipped":0,"passed":1,"unknown":0,"total":1},"items":[{"uid":"8fcc963641b1a19e","reportUrl":"https://zakharovyn.github.io/autotests-ui/3/#testresult/8fcc963641b1a19e","status":"passed","time":{"start":1771497742629,"stop":1771497744651,"duration":2022}}]},"4eff3ab65cbfee2d7a4f9afa9de3d5b8":{"statistic":{"failed":0,"broken":0,"skipped":0,"passed":1,"unknown":0,"total":1},"items":[{"uid":"cb4d77ff10fba85d","reportUrl":"https://zakharovyn.github.io/autotests-ui/3/#testresult/cb4d77ff10fba85d","status":"passed","time":{"start":1771497744875,"stop":1771497746890,"duration":2015}}]},"ca8e4005ae6743a7222896e350ca43ee":{"statistic":{"failed":0,"broken":0,"skipped":0,"passed":1,"unknown":0,"total":1},"items":[{"uid":"bf636272eaa3945","reportUrl":"https://zakharovyn.github.io/autotests-ui/3/#testresult/bf636272eaa3945","status":"passed","time":{"start":1771497753909,"stop":1771497753909,"duration":0}}]},"18e044e52be5dd8e37ea09785c7c2820":{"statistic":{"failed":0,"broken":0,"skipped":0,"passed":1,"unknown":0,"total":1},"items":[{"uid":"132c2c4f973ee1a3","reportUrl":"https://zakharovyn.github.io/autotests-ui/3/#testresult/132c2c4f973ee1a3","status":"passed","time":{"start":1771497751577,"stop":1771497753848,"duration":2271}}]},"8b96ff728ee484169780257b0eef330c":{"statistic":{"failed":0,"broken":0,"skipped":0,"passed":1,"unknown":0,"total":1},"items":[{"uid":"97cdb022e7d7bc1b","reportUrl":"https://zakharovyn.github.io/autotests-ui/3/#testresult/97cdb022e7d7bc1b","status":"passed","time":{"start":1771497753906,"stop":1771497753907,"duration":1}}]},"6f43f9e252940c24500c899b6fa77769":{"statistic":{"failed":0,"broken":0,"skipped":0,"passed":1,"unknown":0,"total":1},"items":[{"uid":"470261e7aaa487b4","reportUrl":"https://zakharovyn.github.io/autotests-ui/3/#testresult/470261e7aaa487b4","status":"passed","time":{"start":1771497744920,"stop":1771497748256,"duration":3336}}]},"2665a68cc041e66979fef8ac01824763":{"statistic":{"failed":0,"broken":0,"skipped":0,"passed":1,"unknown":0,"total":1},"items":[{"uid":"77f0a274378fbe71","reportUrl":"https://zakharovyn.github.io/autotests-ui/3/#testresult/77f0a274378fbe71","status":"passed","time":{"start":1771497755105,"stop":1771497756805,"duration":1700}}]},"285e2ddca4f920412b09d48f20bed789":{"statistic":{"failed":0,"broken":0,"skipped":0,"passed":1,"unknown":0,"total":1},"items":[{"uid":"29b677bac50da5fa","reportUrl":"https://zakharovyn.github.io/autotests-ui/3/#testresult/29b677bac50da5fa","status":"passed","time":{"start":1771497742627,"stop":1771497744722,"duration":2095}}]},"8f3b2a73e85056bb5a43c5581514322c":{"statistic":{"failed":0,"broken":0,"skipped":0,"passed":1,"unknown":0,"total":1},"items":[{"uid":"f2e4104c871eb690","reportUrl":"https://zakharovyn.github.io/autotests-ui/3/#testresult/f2e4104c871eb690","status":"passed","time":{"start":1771497753898,"stop":1771497753898,"duration":0}}]},"e51f5dff523be524f1fabc3eaf9ce86d":{"statistic":{"failed":0,"broken":0,"skipped":0,"passed":1,"unknown":0,"total":1},"items":[{"uid":"1167fd305252ae3","reportUrl":"https://zakharovyn.github.io/autotests-ui/3/#testresult/1167fd305252ae3","status":"passed","time":{"start":1771497748961,"stop":1771497750740,"duration":1779}}]},"52819afde9c88e9964383828876debff":{"statistic":{"failed":0,"broken":0,"skipped":0,"passed":1,"unknown":0,"total":1},"items":[{"uid":"82f75d0b04090833","reportUrl":"https://zakharovyn.github.io/autotests-ui/3/#testresult/82f75d0b04090833","status":"passed","time":{"start":1771497749805,"stop":1771497751400,"duration":1595}}]},"1d1334675366209fc2d6be27b93140d3":{"statistic":{"failed":0,"broken":0,"skipped":0,"passed":1,"unknown":0,"total":1},"items":[{"uid":"a042b349320bb6af","reportUrl":"https://zakharovyn.github.io/autotests-ui/3/#testresult/a042b349320bb6af","status":"passed","time":{"start":1771497753901,"stop":1771497753901,"duration":0}}]}}